dir_ops/__init__.py
dir_ops/__main__.py
dir_ops/base_dir_ops.py
dir_ops/decorators.py
dir_ops/local_dir_ops.py
dir_ops/remote_dir_ops.py
dir_ops/utils.py
kabbes_dir_ops-0.10.0.dist-info/LICENSE
kabbes_dir_ops-0.10.0.dist-info/METADATA
kabbes_dir_ops-0.10.0.dist-info/WHEEL
kabbes_dir_ops-0.10.0.dist-info/top_level.txt
kabbes_dir_ops-0.10.0.dist-info/RECORD
