Metadata-Version: 2.1
Name: kabbes-dir-ops
Version: 0.10.0
Summary: Handy directory operations
Home-page: https://pypi.org/project/kabbes-dir-ops/
Author: James Kabbes
Author-email: james.kabbes@gmail.com
Project-URL: GitHub, https://github.com/jameskabbes/dir_ops
Project-URL: Documentation, https://jameskabbes.github.io/dir_ops
Classifier: Programming Language :: Python :: 3
Classifier: License :: OSI Approved :: MIT License
Classifier: Operating System :: OS Independent
Requires-Python: >=3.6
License-File: LICENSE
Requires-Dist: kabbes-py-starter
Requires-Dist: kabbes-parent-class
